examples/__init__.py
timepulse/__init__.py
timepulse/data/__init__.py
timepulse/data/data_collection.py
timepulse/metrics/__init__.py
timepulse/metrics/regression_metrics.py
timepulse/models/__init__.py
timepulse/models/lstm.py
timepulse/models/nbeats.py
timepulse/models/nn.py
timepulse/models/xgboost.py
timepulse/processing/__init__.py
timepulse/processing/min_max_scaler.py
timepulse/processing/standard_scaler.py
timepulse/utils/__init__.py
timepulse/utils/models.py
timepulse/utils/splits.py
timepulse-0.3.0.dist-info/LICENSE.md
timepulse-0.3.0.dist-info/METADATA
timepulse-0.3.0.dist-info/WHEEL
timepulse-0.3.0.dist-info/entry_points.txt
timepulse-0.3.0.dist-info/top_level.txt
timepulse-0.3.0.dist-info/RECORD
