Metadata-Version: 2.1
Name: timepulse
Version: 0.3.0
Summary: A set of algorithms to help with timeseries flow
Home-page: https://github.com/squaredev-io/timepulse
Author: SQUAREDEV BV
Author-email: hello@squaredev.io
Keywords: timeseries algorithms ml flow ai python machine learning
Classifier: License :: OSI Approved :: MIT License
Classifier: Programming Language :: Python :: 3
Classifier: Programming Language :: Python :: 3.9
Classifier: Programming Language :: Python :: 3.10
Classifier: Programming Language :: Python :: 3.11
Requires-Python: >=3.9
License-File: LICENSE.md
Requires-Dist: holidays >=0.38
Requires-Dist: joblib >=1.1.1
Requires-Dist: numpy >=1.24.3
Requires-Dist: pandas >=2.0.2
Requires-Dist: pytest >=7.4.3
Requires-Dist: scikit-learn >=1.3.2
Requires-Dist: setuptools >=65.5.0
Requires-Dist: tensorflow >=2.14.0
Requires-Dist: typer >=0.9.0
Requires-Dist: xgboost >=2.0.2
Provides-Extra: dev
Requires-Dist: pytest ; extra == 'dev'
